src/unipay_sdk/__init__.py
src/unipay_sdk/api.py
src/unipay_sdk/enums.py
src/unipay_sdk/pydantic.py
unipay_sdk-0.0.2.dist-info/LICENSE
unipay_sdk-0.0.2.dist-info/METADATA
unipay_sdk-0.0.2.dist-info/WHEEL
unipay_sdk-0.0.2.dist-info/top_level.txt
unipay_sdk-0.0.2.dist-info/RECORD
