Metadata-Version: 2.1
Name: unipay_sdk
Version: 0.0.2
Summary: SDK for UniPay.com payment gateway
Home-page: https://github.com/BeyondUnderstanding/unipay-sdk
Author-email: Evgeniy Finskiy <finskiy.ru@ya.ru>
Project-URL: Homepage, https://github.com/BeyondUnderstanding/unipay-sdk
Project-URL: Bug Tracker, https://github.com/BeyondUnderstanding/unipay-sdk/issues
Classifier: Programming Language :: Python :: 3
Classifier: License :: OSI Approved :: Apache Software License
Classifier: Operating System :: OS Independent
Requires-Python: >=3.7
License-File: LICENSE
Requires-Dist: requests
Requires-Dist: pydantic
